impotsgouvdata/__init__.py
impotsgouvdata/impots_gouv_data.py
impotsgouvdata/models.py
impotsgouvdata-0.1.0.dist-info/WHEEL
impotsgouvdata-0.1.0.dist-info/METADATA
impotsgouvdata-0.1.0.dist-info/RECORD
