Metadata-Version: 2.1
Name: impotsgouvdata
Version: 0.1.0
Summary: Retrieve taxpayer data from impots.gouv.fr.
License: CECILL-C
Author: Pierre Gobin
Author-email: p.dev@gobin.cc
Requires-Python: >=3.10,<4.0
Classifier: License :: CeCILL-C Free Software License Agreement (CECILL-C)
Classifier: Programming Language :: Python :: 3
Classifier: Programming Language :: Python :: 3.10
Classifier: Programming Language :: Python :: 3.11
Requires-Dist: beautifulsoup4 (>=4.12.3,<5.0.0)
Requires-Dist: lxml (>=5.2.2,<6.0.0)
Requires-Dist: requests (>=2.32.3,<3.0.0)
